adder.v
module full_adder(
input A, B, Cin,
output Sum, Cout
);
assign Sum = A ^ B ^ Cin;
assign Cout = (A & B) | ((A ^ B) & Cin);
endmodule

tb_adder.v
module tb_adder;

reg A, B, Cin;
wire Sum, Cout;

full_adder dut (.A(A), .B(B), .Cin(Cin), .Sum(Sum), .Cout(Cout));

initial begin
$dumpfile("wave.vcd");
$dumpvars(0, tb_adder);

$display("A B Cin | Sum Cout");

A=0; B=0; Cin=0; #10;
$display("%b %b %b | %b %b", A, B, Cin, Sum, Cout);

A=0; B=0; Cin=1; #10;
$display("%b %b %b | %b %b", A, B, Cin, Sum, Cout);

A=0; B=1; Cin=0; #10;
$display("%b %b %b | %b %b", A, B, Cin, Sum, Cout);

A=0; B=1; Cin=1; #10;
$display("%b %b %b | %b %b", A, B, Cin, Sum, Cout);

A=1; B=0; Cin=0; #10;
$display("%b %b %b | %b %b", A, B, Cin, Sum, Cout);

A=1; B=0; Cin=1; #10;
$display("%b %b %b | %b %b", A, B, Cin, Sum, Cout);

A=1; B=1; Cin=0; #10;
$display("%b %b %b | %b %b", A, B, Cin, Sum, Cout);

A=1; B=1; Cin=1; #10;
$display("%b %b %b | %b %b", A, B, Cin, Sum, Cout);

$finish;
end

endmodule

wave.vcd
$date
	Mon May 04 19:08:51 2026
$end
$version
	Icarus Verilog
$end
$timescale
	1s
$end
$scope module tb_adder $end
$var wire 1 ! Sum $end
$var wire 1 " Cout $end
$var reg 1 # A $end
$var reg 1 $ B $end
$var reg 1 % Cin $end
$scope module dut $end
$var wire 1 # A $end
$var wire 1 $ B $end
$var wire 1 % Cin $end
$var wire 1 " Cout $end
$var wire 1 ! Sum $end
$upscope $end
$upscope $end
$enddefinitions $end
#0
$dumpvars
0%
0$
0#
0"
0!
$end
#10
1!
1%
#20
0%
1$
#30
1"
0!
1%
#40
0"
1!
0%
0$
1#
#50
1"
0!
1%
#60
0%
1$
#70
1!
1%
